setup.py
praklib/Praktika.py
praklib/__init__.py
praklib.egg-info/PKG-INFO
praklib.egg-info/SOURCES.txt
praklib.egg-info/dependency_links.txt
praklib.egg-info/top_level.txt