Metadata-Version: 2.1
Name: praklib
Version: 0.0.8
Summary: Moje mala knihovna na praktika
Home-page: 
Author: Brystof_Klazek
Author-email: blazekr2@cvut.cz
Classifier: Programming Language :: Python :: 3
Classifier: Operating System :: OS Independent
